THISDLChatBot/Bot.py
THISDLChatBot/CommandProcessor.py
THISDLChatBot/Config.py
THISDLChatBot/Constants.py
THISDLChatBot/Exceptions.py
THISDLChatBot/Friend.py
THISDLChatBot/Group.py
THISDLChatBot/Logger.py
THISDLChatBot/Message.py
THISDLChatBot/MessageProcessor.py
THISDLChatBot/Plugin.py
THISDLChatBot/Types.py
THISDLChatBot/__init__.py
THISDLChatBot-2.0.19.dist-info/LICENSE
THISDLChatBot-2.0.19.dist-info/METADATA
THISDLChatBot-2.0.19.dist-info/WHEEL
THISDLChatBot-2.0.19.dist-info/top_level.txt
THISDLChatBot-2.0.19.dist-info/RECORD
